simple_pipe/__init__.py
simple_pipe-2.0.1.dist-info/LICENSE.md
simple_pipe-2.0.1.dist-info/METADATA
simple_pipe-2.0.1.dist-info/WHEEL
simple_pipe-2.0.1.dist-info/entry_points.txt
simple_pipe-2.0.1.dist-info/top_level.txt
simple_pipe-2.0.1.dist-info/RECORD
