Metadata-Version: 2.1
Name: simple-pipe
Version: 2.0.1
Summary: Function composition for Python
Home-page: https://github.com/sebbekarlsson/simple-pipe
Author: ianertson
Author-email: ianertson@gmail.com
License: UNKNOWN
Platform: UNKNOWN
